cdk_rds_dump/__init__.py
cdk_rds_dump/py.typed
cdk_rds_dump/_jsii/__init__.py
cdk_rds_dump/_jsii/cdk-rds-dump@2.1.11.jsii.tgz
cdk_rds_dump-2.1.11.dist-info/LICENSE
cdk_rds_dump-2.1.11.dist-info/METADATA
cdk_rds_dump-2.1.11.dist-info/WHEEL
cdk_rds_dump-2.1.11.dist-info/top_level.txt
cdk_rds_dump-2.1.11.dist-info/RECORD
